pyterminalx/__init__.py
pyterminalx/commands.py
pyterminalx/example.py
pyterminalx-1.0.4.dist-info/licenses/LICENSE.txt
pyterminalx-1.0.4.dist-info/METADATA
pyterminalx-1.0.4.dist-info/WHEEL
pyterminalx-1.0.4.dist-info/entry_points.txt
pyterminalx-1.0.4.dist-info/top_level.txt
pyterminalx-1.0.4.dist-info/RECORD
