Metadata-Version: 2.4
Name: pyterminalx
Version: 1.0.4
Summary: A Linux Terminal Emulator development Package for various os
Home-page: https://github.com/ap1311/pyterminal
Author: Aarav Shah
Author-email: aaravprogrammers@gmail.com
Classifier: Programming Language :: Python :: 3
Classifier: License :: OSI Approved :: MIT License
Classifier: Operating System :: OS Independent
Classifier: Topic :: Utilities
Classifier: Topic :: System :: Shells
License-File: LICENSE.txt
Requires-Dist: requests
Requires-Dist: pycurl
Dynamic: author
Dynamic: author-email
Dynamic: classifier
Dynamic: description
Dynamic: description-content-type
Dynamic: home-page
Dynamic: license-file
Dynamic: requires-dist
Dynamic: summary
